rapidsockets/__init__.py
rapidsockets/rs.py
rapidsockets-0.0.5.dist-info/METADATA
rapidsockets-0.0.5.dist-info/WHEEL
rapidsockets-0.0.5.dist-info/top_level.txt
rapidsockets-0.0.5.dist-info/RECORD
