Metadata-Version: 2.1
Name: rapidsockets
Version: 0.0.5
Summary: Official Python SDK for the RapidSockets platform
Home-page: https://github.com/rapidsockets/python
Author: RapidSockets
Author-email: support@rapidsockets.com
License: MIT
Keywords: websockets
Platform: UNKNOWN
Requires-Dist: websocket-client
Requires-Dist: requests
